LICENSE
buildgraph/__init__.py
buildgraph/base_step.py
buildgraph/binding.py
buildgraph/colours.py
buildgraph/context.py
buildgraph/exception.py
buildgraph/graph.py
buildgraph/steps.py
buildgraph/tabulated_writer.py
buildgraph/timer.py
buildgraph/utils.py
buildgraph-0.0.7.dist-info/LICENSE
buildgraph-0.0.7.dist-info/WHEEL
buildgraph-0.0.7.dist-info/METADATA
buildgraph-0.0.7.dist-info/RECORD
