Metadata-Version: 2.1
Name: buildgraph
Version: 0.0.7
Summary: Tools for building
Home-page: https://github.com/ubuntom/buildgraph
License: MIT
Author: ubuntom
Requires-Python: >=3.7,<4.0
Classifier: License :: OSI Approved :: MIT License
Classifier: Operating System :: OS Independent
Classifier: Programming Language :: Python :: 3
Classifier: Programming Language :: Python :: 3.10
Classifier: Programming Language :: Python :: 3.7
Classifier: Programming Language :: Python :: 3.8
Classifier: Programming Language :: Python :: 3.9
